{
  "threshold": "5%",
  "totalDpesInFile": 10000,
  "nbValidDpe": 10000,
  "nbInvalidDpeVersion": 0,
  "nbExcludedDpe": 0,
  "nbAllChecksBelowThreshold": 6056,
  "successRatio": "60.56 %",
  "dpeRunFailed": ["2291E3237230K", "2368E3643180A", "2359E2821117W", "2291E3237200G"],
  "checks": {
    "deperdition_mur": { "nbBelowThreshold": 9710, "successRatio": "97.10 %" },
    "deperdition_baie_vitree": { "nbBelowThreshold": 9865, "successRatio": "98.65 %" },
    "deperdition_plancher_bas": { "nbBelowThreshold": 9600, "successRatio": "96.00 %" },
    "deperdition_plancher_haut": { "nbBelowThreshold": 9958, "successRatio": "99.58 %" },
    "deperdition_porte": { "nbBelowThreshold": 9908, "successRatio": "99.08 %" },
    "deperdition_renouvellement_air": { "nbBelowThreshold": 9895, "successRatio": "98.95 %" },
    "hperm": { "nbBelowThreshold": 9671, "successRatio": "96.71 %" },
    "deperdition_pont_thermique": { "nbBelowThreshold": 9768, "successRatio": "97.68 %" },
    "surface_sud_equivalente": { "nbBelowThreshold": 9808, "successRatio": "98.08 %" },
    "besoin_ecs": { "nbBelowThreshold": 9986, "successRatio": "99.86 %" },
    "besoin_ch": { "nbBelowThreshold": 9387, "successRatio": "93.87 %" },
    "conso_ecs": { "nbBelowThreshold": 8729, "successRatio": "87.29 %" },
    "conso_ch": { "nbBelowThreshold": 9037, "successRatio": "90.37 %" },
    "conso_auxiliaire_distribution_ch": { "nbBelowThreshold": 7225, "successRatio": "72.25 %" },
    "conso_auxiliaire_generation_ch": { "nbBelowThreshold": 8915, "successRatio": "89.15 %" },
    "conso_auxiliaire_generation_ecs": { "nbBelowThreshold": 9381, "successRatio": "93.81 %" },
    "conso_auxiliaire_ventilation": { "nbBelowThreshold": 9486, "successRatio": "94.86 %" },
    "ep_conso_5_usages": { "nbBelowThreshold": 8430, "successRatio": "84.30 %" },
    "ep_conso_5_usages_m2": { "nbBelowThreshold": 8416, "successRatio": "84.16 %" },
    "emission_ges_5_usages": { "nbBelowThreshold": 6580, "successRatio": "65.80 %" },
    "emission_ges_5_usages_m2": { "nbBelowThreshold": 6690, "successRatio": "66.90 %" },
    "conso_auxiliaire_distribution_ecs": { "nbBelowThreshold": 5497, "successRatio": "54.97 %" }
  }
}
